wyzepy/__init__.py
wyzepy/get_hour.py
wyzepy/process_video.py
wyzepy-0.1.2.dist-info/METADATA
wyzepy-0.1.2.dist-info/WHEEL
wyzepy-0.1.2.dist-info/top_level.txt
wyzepy-0.1.2.dist-info/RECORD
